Metadata-Version: 2.1
Name: ShallowTree
Version: 0.0.10
Summary: Shallow decision trees for explainable clustering
Home-page: https://github.com/lmurtinho/ShallowTree
Author: Lucas Murtinho
Author-email: lucas.murtinho@gmail.com
License: MIT
Platform: UNKNOWN
